<?xml version="1.0" encoding="UTF-8" standalone="yes"?>
<EEMResp>
    <OpenCaseInfoList>
        <openCaseInfo caseCode="2017050044" caseEndTime="" caseName="106年5月16日EMIC操作演練中央專案" caseStartTime="2017/05/16 09:01" cityCode="" disName="風災" eocName="中央災害應變中心" openTier="1"/>
        <openCaseInfo caseCode="2017050044" caseEndTime="" caseName="106年5月EMIC第一種型態演練" caseStartTime="2017/05/16 11:57" cityCode="65" disName="風災" eocName="新北市災害應變中心" openTier="2"/>
        <openCaseInfo caseCode="2017050044" caseEndTime="2017/05/16 18:02" caseName="106年5月16日EMIC操作演練中央專案" caseStartTime="2017/05/16 09:17" cityCode="10002" disName="風災" eocName="宜蘭縣災害應變中心" openTier="2"/>
        <openCaseInfo caseCode="2017050044" caseEndTime="" caseName="106年5月16日EMIC操作演練中央專案" caseStartTime="2017/05/16 13:56" cityCode="10004" disName="水災" eocName="新竹縣災害應變中心" openTier="2"/>
        <openCaseInfo caseCode="2017050044" caseEndTime="2017/05/16 13:25" caseName="106年5月16日EMIC操作演練中央專案" caseStartTime="2017/05/16 13:24" cityCode="10004" disName="爆炸" eocName="新竹縣災害應變中心" openTier="2"/>
        <openCaseInfo caseCode="2017050044" caseEndTime="2017/05/16 13:27" caseName="106年5月16日EMIC操作演練中央專案" caseStartTime="2017/05/16 13:25" cityCode="10004" disName="水災" eocName="新竹縣災害應變中心" openTier="3"/>
        <openCaseInfo caseCode="2017050044" caseEndTime="2017/05/16 13:49" caseName="106年5月16日EMIC操作演練中央專案" caseStartTime="2017/05/16 13:33" cityCode="10004" disName="風災" eocName="新竹縣災害應變中心" openTier="1"/>
        <openCaseInfo caseCode="2017050044" caseEndTime="2017/05/16 13:24" caseName="106年5月16日EMIC操作演練中央專案" caseStartTime="2017/05/16 13:13" cityCode="10004" disName="風災" eocName="新竹縣災害應變中心" openTier="2"/>
        <openCaseInfo caseCode="2017050044" caseEndTime="2017/05/16 09:28" caseName="106年5月16日EMIC操作演練中央專案" caseStartTime="2017/05/16 09:26" cityCode="10004" disName="風災" eocName="新竹縣災害應變中心" openTier="1"/>
        <openCaseInfo caseCode="2017050044" caseEndTime="" caseName="106年5月16日EMIC操作演練中央專案" caseStartTime="2017/05/16 09:05" cityCode="10007" disName="風災" eocName="彰化縣災害應變中心" openTier="2"/>
        <openCaseInfo caseCode="2017050044" caseEndTime="2017/05/16 17:35" caseName="106年5月16日EMIC操作演練中央專案" caseStartTime="2017/05/16 09:50" cityCode="10009" disName="風災" eocName="雲林縣災害應變中心" openTier="3"/>
        <openCaseInfo caseCode="2017050044" caseEndTime="2017/05/16 18:10" caseName="106年5月16日EMIC操作演練中央專案" caseStartTime="2017/05/16 09:30" cityCode="10015" disName="風災" eocName="花蓮縣災害應變中心" openTier="2"/>
        <openCaseInfo caseCode="2017050044" caseEndTime="" caseName="106年5月16日EMIC操作演練中央專案" caseStartTime="2017/05/16 09:20" cityCode="10017" disName="風災" eocName="基隆市災害應變中心" openTier="2"/>
        <openCaseInfo caseCode="2017050044" caseEndTime="" caseName="106年5月16日EMIC操作演練中央專案" caseStartTime="2017/05/16 09:37" cityCode="66" disName="風災" eocName="臺中市災害應變中心" openTier="2"/>
    </OpenCaseInfoList>
    <resultCode>S</resultCode>
    <resultText>SUCCESS</resultText>
</EEMResp>
