{"result":{"offset":0,"limit":10000,"count":99,"sort":"","results":[{"_id":"1","AC_NO":"102004900","ST_NO":"1","SNO":"298","APPMODE":"0","X":"302738.601","Y":"2770178.978","APPTIME":"1060509093145","APP_NAME":"台電輸變電","C_NAME":"中正","ADDR":"紹興南街17~21-3號與仁愛路1段1~19號","CB_DA":"1020708","CE_DA":"1060728","CO_TI":"依交維計畫訂定時間施工 2月11日-3月2日禁止道路施工","TC_MA":"劉朝福","TC_TL":"0920334070","TC_MA3":"連彥宇","TC_TL3":"0937141297","NPURP":"新設、人手孔新設","DTYPE":null},{"_id":"2","AC_NO":"105004311-2","ST_NO":"1","SNO":"82","APPMODE":"0","X":"301530.074","Y":"2780056.766","APPTIME":"1060509094614","APP_NAME":"衛工處","C_NAME":"北投","ADDR":"奇岩路253號附近地區","CB_DA":"1051024","CE_DA":"1060627","CO_TI":"日間施工9時30分至16時","TC_MA":"蕭志宏","TC_TL":"0933063248","TC_MA3":"洪基富","TC_TL3":"0913550560","NPURP":"市政建設","DTYPE":null},{"_id":"3","AC_NO":"105004679","ST_NO":"1","SNO":"21","APPMODE":"0","X":"303369.731","Y":"2779292.252","APPTIME":"1060509092633","APP_NAME":"自來水陽明","C_NAME":"士林","ADDR":"天玉街38巷以東、中山北路7段以西、中山北路7段141巷以南及天母西路以北","CB_DA":"1050718","CE_DA":"1060831","CO_TI":"日間施工9時30分至16時，巷弄道路週休二日不得施工","TC_MA":"莊家榮","TC_TL":"0979213299","TC_MA3":"朱海平","TC_TL3":"0921082526","NPURP":"市政建設","DTYPE":null},{"_id":"4","AC_NO":"105006528-3","ST_NO":"1","SNO":"11","APPMODE":"0","X":"302339.056","Y":"2772550.644","APPTIME":"1060509092640","APP_NAME":"台電市區","C_NAME":"大同","ADDR":"錦西街52巷口至巷內16號邊及錦西街口至雙連街65巷12號前","CB_DA":"1051019","CE_DA":"1060510","CO_TI":"日間施工9時30分至16時","TC_MA":"李勇霖","TC_TL":"0953501485","TC_MA3":"李吉龍","TC_TL3":"0975517262","NPURP":"民生需求-新建房屋","DTYPE":null},{"_id":"5","AC_NO":"105007205","ST_NO":"1","SNO":"6","APPMODE":"0","X":"302035.409","Y":"2772490.847","APPTIME":"1060509094035","APP_NAME":"台電市區","C_NAME":"大同","ADDR":"錦西街174號前至錦西公園前及歸綏街97巷16號前至錦西街口","CB_DA":"1051116","CE_DA":"1060510","CO_TI":"日間施工9時30分至16時","TC_MA":"朱家弘","TC_TL":"0933858024","TC_MA3":"謝佳良","TC_TL3":"0978721677","NPURP":"管線單位需求-配合拆遷","DTYPE":null},{"_id":"6","AC_NO":"10500833","ST_NO":"0","SNO":"624","APPMODE":"5","X":"301202.049","Y":"2775438.165","APPTIME":"1060509102154","APP_NAME":"新工處","C_NAME":"士林","ADDR":"一般橋梁-重陽橋引道","CB_DA":"1060129","CE_DA":"1060601","CO_TI":null,"TC_MA":"李靖淵","TC_TL":"0933889594","TC_MA3":"謝靖毅","TC_TL3":"0917558991","NPURP":"道路維護施工","DTYPE":null},{"_id":"7","AC_NO":"10501154","ST_NO":"0","SNO":"105","APPMODE":"5","X":"302460.899","Y":"2776936.29","APPTIME":"1060509090447","APP_NAME":"新工處","C_NAME":"士林","ADDR":"一般橋梁-承德橋及文昌橋","CB_DA":"1050622","CE_DA":"1060918","CO_TI":null,"TC_MA":"邱益成","TC_TL":"0920336311","TC_MA3":"高凡宸","TC_TL3":"0972048004","NPURP":"道路維護施工","DTYPE":null},{"_id":"8","AC_NO":"10501707","ST_NO":"0","SNO":"250","APPMODE":"5","X":"300972.793","Y":"2775374.399","APPTIME":"1060509084625","APP_NAME":"新工處","C_NAME":"士林","ADDR":"重陽橋","CB_DA":"1050805","CE_DA":"1061124","CO_TI":null,"TC_MA":"高嘉宏","TC_TL":"0982276381","TC_MA3":"王志峰","TC_TL3":"0921155251","NPURP":"道路維護施工","DTYPE":null},{"_id":"9","AC_NO":"10502781","ST_NO":"0","SNO":"4","APPMODE":"5","X":"301054.309","Y":"2771378.559","APPTIME":"1060425081354","APP_NAME":"新工處","C_NAME":"中正","ADDR":"忠孝西路(環河南路至中山南路)及周邊道路、人行道範圍","CB_DA":"1051121","CE_DA":"1060514","CO_TI":null,"TC_MA":"韋肇煜","TC_TL":"0937054882","TC_MA3":"紀志明","TC_TL3":"0935580612","NPURP":"道路維護施工","DTYPE":null},{"_id":"10","AC_NO":"10502967","ST_NO":"0","SNO":"148","APPMODE":"5","X":"300023.077","Y":"2767541.337","APPTIME":"1060509080647","APP_NAME":"新工處","C_NAME":"萬華","ADDR":"華中橋","CB_DA":"1051209","CE_DA":"1071124","CO_TI":null,"TC_MA":"黃觀林","TC_TL":"0980224132","TC_MA3":"鄭秉燁","TC_TL3":"0963474234","NPURP":"道路維護施工","DTYPE":null},{"_id":"11","AC_NO":"106000176","ST_NO":"1","SNO":"46","APPMODE":"0","X":"302217.931","Y":"2776955.512","APPTIME":"1060509084845","APP_NAME":"衛工處","C_NAME":"士林","ADDR":"文林北路5巷建德橋旁","CB_DA":"1060110","CE_DA":"1060630","CO_TI":"全日施工(配合防汛期)","TC_MA":"宋新炫","TC_TL":"0933845115","TC_MA3":"賴正雄","TC_TL3":"0982775056","NPURP":"市政建設","DTYPE":null},{"_id":"12","AC_NO":"106000331-1","ST_NO":"1","SNO":"1","APPMODE":"0","X":"304880.173","Y":"2776663.227","APPTIME":"1060509095623","APP_NAME":"電信士林","C_NAME":"士林","ADDR":"至善路2段1巷1之1號及25巷口共修管2處","CB_DA":"1060509","CE_DA":"1060510","CO_TI":"日間施工10時至16時","TC_MA":"王芬滄","TC_TL":"0937026747","TC_MA3":"李賢德","TC_TL3":"0929858518","NPURP":"民生需求-舊有用戶","DTYPE":null},{"_id":"13","AC_NO":"106000465","ST_NO":"1","SNO":"3","APPMODE":"0","X":"306652.416","Y":"2772635.144","APPTIME":"1060509093052","APP_NAME":"台電市區","C_NAME":"松山","ADDR":"富錦街429巷口至457號前","CB_DA":"1060301","CE_DA":"1060509","CO_TI":"日間施工9時30分至16時","TC_MA":"陳柏蒼","TC_TL":"0919109319","TC_MA3":"李志偉","TC_TL3":"0939359772","NPURP":"民生需求-舊有用戶","DTYPE":null},{"_id":"14","AC_NO":"106000614-1","ST_NO":"1","SNO":"9","APPMODE":"0","X":"301939.831","Y":"2772475.542","APPTIME":"1060509100405","APP_NAME":"大台北瓦斯","C_NAME":"大同","ADDR":"寧夏路89號至95號前","CB_DA":"1060301","CE_DA":"1060513","CO_TI":"依交維計畫立井為日間10至16時施工，新舊管線銜接施工為夜間23至5時30分，潛鑽24小時施工","TC_MA":"黃惟斌","TC_TL":"0922747320","TC_MA3":"巴馥馨","TC_TL3":"0955304666","NPURP":"管線單位需求-既設管線改善","DTYPE":null},{"_id":"15","AC_NO":"106000712","ST_NO":"1","SNO":"23","APPMODE":"0","X":"304463.151","Y":"2768613.124","APPTIME":"1060509093400","APP_NAME":"國立臺北教育大學附設實驗國民小學","C_NAME":"大安","ADDR":"和平東路2段90巷(76巷17弄口北側至76巷2弄口南側)","CB_DA":"1060223","CE_DA":"1060529","CO_TI":"日間施工9時30分至16時","TC_MA":"王君?","TC_TL":"0933157926","TC_MA3":"林詠峰","TC_TL3":"0927727203","NPURP":"管線單位需求-既設管線改善","DTYPE":null},{"_id":"16","AC_NO":"106000982","ST_NO":"1","SNO":"14","APPMODE":"0","X":"307547.651","Y":"2770866.805","APPTIME":"1060509093300","APP_NAME":"自來水東區","C_NAME":"信義","ADDR":"永吉路120巷(松隆路口至忠孝東路口)單號側、永吉路120巷43弄2號及10號、永吉路180巷67弄近松信路口","CB_DA":"1060324","CE_DA":"1060516","CO_TI":"依交維計畫訂定時間施工  日間施工9時30分至16時 巷弄道路週休二日不得施工","TC_MA":"許哲瑋","TC_TL":"0921802648","TC_MA3":"陳義貴","TC_TL3":"0921617848","NPURP":"市政建設","DTYPE":null},{"_id":"17","AC_NO":"106000986-1","ST_NO":"1","SNO":"2","APPMODE":"0","X":"302011.206","Y":"2773171.306","APPTIME":"1060509093308","APP_NAME":"金頻道有線","C_NAME":"大同","ADDR":"昌吉街72號前","CB_DA":"1060508","CE_DA":"1060510","CO_TI":"日間施工9時30分至16時","TC_MA":"郭得仁","TC_TL":"0982731078","TC_MA3":"賴致瑋","TC_TL3":"0931087443","NPURP":"管線單位需求-建設需求","DTYPE":null},{"_id":"18","AC_NO":"106001010","ST_NO":"1","SNO":"5","APPMODE":"0","X":"305708.582","Y":"2766097.451","APPTIME":"1060509100046","APP_NAME":"自來水工總","C_NAME":"文山","ADDR":"興隆路2段與福興路口共2處探挖","CB_DA":"1060313","CE_DA":"1060707","CO_TI":"依交維計畫推進井24小時施工及日間施工10時至16時","TC_MA":"陳志強","TC_TL":"0938929877","TC_MA3":"蔡明旭","TC_TL3":"0926383840","NPURP":"管線單位需求-建設需求","DTYPE":null},{"_id":"19","AC_NO":"1060012843","ST_NO":"0","SNO":"1","APPMODE":"6","X":"307299.406","Y":"2775060.213","APPTIME":"1060509113955","APP_NAME":"電信東區","C_NAME":"內湖","ADDR":"內湖路1段323巷3弄口","CB_DA":"1060429","CE_DA":"1060727","CO_TI":"09:30-16:00","TC_MA":"林光興","TC_TL":"0928840294","TC_MA3":"林威助","TC_TL3":"0988707608","NPURP":"人手孔施工","DTYPE":null},{"_id":"20","AC_NO":"1060013894","ST_NO":"0","SNO":"5","APPMODE":"6","X":"306781.505","Y":"2764675.954","APPTIME":"1060509093533","APP_NAME":"水利處","C_NAME":"文山","ADDR":"木柵路2段","CB_DA":"1060425","CE_DA":"1060509","CO_TI":"09:30-16:00","TC_MA":"顏慧雅","TC_TL":"0917281126","TC_MA3":"張米豆","TC_TL3":"0925540588","NPURP":"人手孔施工","DTYPE":null},{"_id":"21","AC_NO":"106001390","ST_NO":"1","SNO":"2","APPMODE":"0","X":"301078.396","Y":"2779784.977","APPTIME":"1060509093122","APP_NAME":"電信士林","C_NAME":"北投","ADDR":"公館路292巷8號至19號旁","CB_DA":"1060417","CE_DA":"1060509","CO_TI":"日間施工9時30分至16時","TC_MA":"王芬滄","TC_TL":"0937026747","TC_MA3":"陳威龍","TC_TL3":"0913125552","NPURP":"民生需求-舊有用戶","DTYPE":null},{"_id":"22","AC_NO":"106001423-1","ST_NO":"1","SNO":"1","APPMODE":"0","X":"301347.422","Y":"2771948.124","APPTIME":"1060509093024","APP_NAME":"長德有線","C_NAME":"大同","ADDR":"西寧北路67-1號前","CB_DA":"1060509","CE_DA":"1060511","CO_TI":"日間施工10時至16時","TC_MA":"張皓強","TC_TL":"0920656179","TC_MA3":"馬偉鋆","TC_TL3":"0978223858","NPURP":"市政建設","DTYPE":null},{"_id":"23","AC_NO":"1060014790","ST_NO":"0","SNO":"5","APPMODE":"6","X":"302290.319","Y":"2776138.548","APPTIME":"1060509093828","APP_NAME":"自來水工總","C_NAME":"士林","ADDR":"士商路123號及基河路240巷口","CB_DA":"1060506","CE_DA":"1060510","CO_TI":"09:30-16:00","TC_MA":"林尚祺","TC_TL":"0979213326","TC_MA3":"鄭詠霖","TC_TL3":"0906898639","NPURP":"人手孔施工","DTYPE":null},{"_id":"24","AC_NO":"1060014790","ST_NO":"0","SNO":"6","APPMODE":"6","X":"302476.786","Y":"2775909.508","APPTIME":"1060509095357","APP_NAME":"自來水工總","C_NAME":"士林","ADDR":"士商路123號及基河路240巷口","CB_DA":"1060506","CE_DA":"1060510","CO_TI":"09:30-16:00","TC_MA":"林尚祺","TC_TL":"0979213326","TC_MA3":"鄭詠霖","TC_TL3":"0906898639","NPURP":"人手孔施工","DTYPE":null},{"_id":"25","AC_NO":"1060014809","ST_NO":"0","SNO":"5","APPMODE":"6","X":"302603.496","Y":"2775726.494","APPTIME":"1060509101907","APP_NAME":"自來水工總","C_NAME":"士林","ADDR":"士商路基河路188巷口及承德路4段大南路口","CB_DA":"1060506","CE_DA":"1060510","CO_TI":"09:30-16:00","TC_MA":"林尚祺","TC_TL":"0979213326","TC_MA3":"鄭詠霖","TC_TL3":"0906898639","NPURP":"人手孔施工","DTYPE":null},{"_id":"26","AC_NO":"106001481","ST_NO":"1","SNO":"2","APPMODE":"3","X":"302768.893","Y":"2776120.491","APPTIME":"1060509110832","APP_NAME":"電信士林","C_NAME":"士林","ADDR":"福德路48巷16~8號修管","CB_DA":"1060502","CE_DA":"1060503","CO_TI":"日間施工9時30分至16時","TC_MA":"王芬滄","TC_TL":"0937026747","TC_MA3":"黃滿榮","TC_TL3":"0978087325","NPURP":"民生需求-舊有用戶","DTYPE":null},{"_id":"27","AC_NO":"106001499-1","ST_NO":"1","SNO":"1","APPMODE":"0","X":"302635.804","Y":"2771981.557","APPTIME":"1060509094714","APP_NAME":"自來水北區","C_NAME":"中山","ADDR":"中山北路2段44巷11號旁(民安里)","CB_DA":"1060508","CE_DA":"1060510","CO_TI":"日間施工9時30分至16時","TC_MA":"蘇煥格","TC_TL":"0979213285","TC_MA3":"葉文賢","TC_TL3":"0921193804","NPURP":"管線單位需求-既設管線改善","DTYPE":null},{"_id":"28","AC_NO":"1060015483","ST_NO":"0","SNO":"2","APPMODE":"6","X":"304970.707","Y":"2765556.216","APPTIME":"1060509110046","APP_NAME":"水利處","C_NAME":"文山","ADDR":"景興路40號前","CB_DA":"1060509","CE_DA":"1060523","CO_TI":"09:30-16:00","TC_MA":"高歆翔","TC_TL":"0919576896","TC_MA3":"陳言杰","TC_TL3":"0980047077","NPURP":"人手孔施工","DTYPE":null},{"_id":"29","AC_NO":"1060015594","ST_NO":"0","SNO":"2","APPMODE":"6","X":"305571.713","Y":"2772235.72","APPTIME":"1060509112152","APP_NAME":"電信北區","C_NAME":"松山","ADDR":"明生東路4段52號~56巷.敦化北路199巷一帶","CB_DA":"1060505","CE_DA":"1060509","CO_TI":"09:30-16:00","TC_MA":"方明進","TC_TL":"方明進","TC_MA3":"賴漢文","TC_TL3":"0937948483","NPURP":"人手孔施工","DTYPE":null},{"_id":"30","AC_NO":"1060015650","ST_NO":"0","SNO":"1","APPMODE":"6","X":"305246.442","Y":"2765830.776","APPTIME":"1060509111335","APP_NAME":"電信南區","C_NAME":"文山","ADDR":"興隆路2段97號旁","CB_DA":"1060508","CE_DA":"1060510","CO_TI":"09:30-16:00","TC_MA":"林光興","TC_TL":"0928840294","TC_MA3":"曾世賢","TC_TL3":"0919039190","NPURP":"人手孔施工","DTYPE":null},{"_id":"31","AC_NO":"106001573","ST_NO":"1","SNO":"1","APPMODE":"0","X":"309571.613","Y":"2772547.048","APPTIME":"1060509105826","APP_NAME":"公園處","C_NAME":"內湖","ADDR":"新明路95巷口","CB_DA":"1060508","CE_DA":"1060510","CO_TI":"依交維計畫訂定時間施工  日間施工9時30分至16時","TC_MA":"高鼎易","TC_TL":"0952033110","TC_MA3":"余誌峰","TC_TL3":"0925987647","NPURP":"市政建設","DTYPE":null},{"_id":"32","AC_NO":"106001579","ST_NO":"1","SNO":"4","APPMODE":"0","X":"301804.443","Y":"2776699.912","APPTIME":"1060509091245","APP_NAME":"台電供電","C_NAME":"士林","ADDR":"士商路口與承德路5段轉基河路至文林路587巷(美崙公園)","CB_DA":"1060417","CE_DA":"1060831","CO_TI":"依交維計畫施工，潛盾08:00~22:00，明挖日間施工10:00~16:00。","TC_MA":"王相禹","TC_TL":"0988692822","TC_MA3":"王義昌","TC_TL3":"0933120396","NPURP":"14","DTYPE":null},{"_id":"33","AC_NO":"1060015861","ST_NO":"0","SNO":"1","APPMODE":"6","X":"301923.611","Y":"2769004.133","APPTIME":"1060509112845","APP_NAME":"台電市區","C_NAME":"中正","ADDR":"泉州街10號.57號","CB_DA":"1060509","CE_DA":"1060519","CO_TI":"09:30-16:00","TC_MA":"田景元","TC_TL":"0922700973","TC_MA3":"黃國慶","TC_TL3":"0981425818","NPURP":"人手孔施工","DTYPE":null},{"_id":"34","AC_NO":"1060015869","ST_NO":"0","SNO":"1","APPMODE":"6","X":"301934.782","Y":"2768964.38","APPTIME":"1060509112142","APP_NAME":"台電市區","C_NAME":"中正","ADDR":"泉州街41-1號.69號","CB_DA":"1060509","CE_DA":"1060519","CO_TI":"09:30-16:00","TC_MA":"田景元","TC_TL":"0922700973","TC_MA3":"林智賢","TC_TL3":"0905060835","NPURP":"人手孔施工","DTYPE":null},{"_id":"35","AC_NO":"1060015909","ST_NO":"0","SNO":"1","APPMODE":"6","X":"304587.551","Y":"2765886.183","APPTIME":"1060509105002","APP_NAME":"台電南區","C_NAME":"文山","ADDR":"景隆街21號前及景隆街19巷1號等共3處","CB_DA":"1060509","CE_DA":"1060511","CO_TI":"09:30-16:00","TC_MA":"張士卿","TC_TL":"0988383486","TC_MA3":"蔡順興","TC_TL3":"0927906635","NPURP":"人手孔施工","DTYPE":null},{"_id":"36","AC_NO":"1060015956","ST_NO":"0","SNO":"1","APPMODE":"6","X":"308601.253","Y":"2770400.323","APPTIME":"1060509101324","APP_NAME":"新台北有線","C_NAME":"信義","ADDR":"林口街114巷及福德街84巷及信義路6段","CB_DA":"1060509","CE_DA":"1060513","CO_TI":"09:30-16:00","TC_MA":"鄂志成","TC_TL":"0955000631","TC_MA3":"郭金富","TC_TL3":"0972283339","NPURP":"人手孔施工","DTYPE":null},{"_id":"37","AC_NO":"1060015964","ST_NO":"0","SNO":"1","APPMODE":"6","X":"303622.306","Y":"2768498.674","APPTIME":"1060509093353","APP_NAME":"北都有線電視","C_NAME":"大安","ADDR":"泰順街龍坡里","CB_DA":"1060509","CE_DA":"1060513","CO_TI":"09:30-16:00","TC_MA":"王朝文","TC_TL":"A123567705","TC_MA3":"林俊欽","TC_TL3":"0906787089","NPURP":"人手孔施工","DTYPE":null},{"_id":"38","AC_NO":"106001597","ST_NO":"1","SNO":"16","APPMODE":"0","X":"300754.666","Y":"2780924.935","APPTIME":"1060509093841","APP_NAME":"衛工處","C_NAME":"北投","ADDR":"光明路北投區光明路185號至205號","CB_DA":"1060419","CE_DA":"1060531","CO_TI":"日間施工9時30分至16時","TC_MA":"蕭志宏","TC_TL":"0933063248","TC_MA3":"陳威廷","TC_TL3":"0913550560","NPURP":"市政建設","DTYPE":null},{"_id":"39","AC_NO":"1060015971","ST_NO":"0","SNO":"1","APPMODE":"6","X":"302571.359","Y":"2772767.939","APPTIME":"1060509082836","APP_NAME":"衛工處","C_NAME":"中山","ADDR":"天祥路48號至64號及天祥路47巷全線其後巷與附近周邊地區","CB_DA":"1060509","CE_DA":"1060513","CO_TI":"09:30-16:00","TC_MA":"胡志忠","TC_TL":"胡志忠","TC_MA3":"陳春進","TC_TL3":"0928201111","NPURP":"人手孔施工","DTYPE":null},{"_id":"40","AC_NO":"1060016017","ST_NO":"0","SNO":"1","APPMODE":"6","X":"304254.672","Y":"2769081.878","APPTIME":"1060509104135","APP_NAME":"台灣智慧光網","C_NAME":"大安","ADDR":"建國南路2段149~231號，新生南路2段，青田街七巷，和平東路2段(以上包含本線及巷弄)","CB_DA":"1060509","CE_DA":"1060513","CO_TI":"09:30-16:00","TC_MA":"練怡孝","TC_TL":"0985453955","TC_MA3":"林昆毅","TC_TL3":"0912924268","NPURP":"人手孔施工","DTYPE":null},{"_id":"41","AC_NO":"1060016025","ST_NO":"0","SNO":"1","APPMODE":"6","X":"303068.698","Y":"2773460.714","APPTIME":"1060509103538","APP_NAME":"台電市區","C_NAME":"中山","ADDR":"民族東路(林森北路至雙城街附近一帶)","CB_DA":"1060509","CE_DA":"1060510","CO_TI":"09:30-16:00","TC_MA":"吳鎮琪","TC_TL":"0960652616","TC_MA3":"蕭烽祺","TC_TL3":"0938802611","NPURP":"人手孔施工","DTYPE":null},{"_id":"42","AC_NO":"1060016051","ST_NO":"0","SNO":"2","APPMODE":"6","X":"303061.731","Y":"2775591.845","APPTIME":"1060509100239","APP_NAME":"電信士林","C_NAME":"士林","ADDR":"文林路89至99號一帶","CB_DA":"1060509","CE_DA":"1060510","CO_TI":"09:30-16:00","TC_MA":"陳振恭","TC_TL":"0988166766","TC_MA3":"楊瑞宏","TC_TL3":"0911248308","NPURP":"人手孔施工","DTYPE":null},{"_id":"43","AC_NO":"106001644","ST_NO":"1","SNO":"1","APPMODE":"0","X":"306830.306","Y":"2764893.532","APPTIME":"1060509103123","APP_NAME":"電信南區","C_NAME":"文山","ADDR":"木柵路2段109巷135號","CB_DA":"1060509","CE_DA":"1060510","CO_TI":"日間施工9時30分至16時","TC_MA":"葉其全","TC_TL":"0937097534","TC_MA3":"林奕宏","TC_TL3":"0972702591","NPURP":"管線單位需求-既設管線改善","DTYPE":null},{"_id":"44","AC_NO":"106001662","ST_NO":"1","SNO":"2","APPMODE":"3","X":"310373.019","Y":"2774640.028","APPTIME":"1060509102501","APP_NAME":"台電北區","C_NAME":"內湖","ADDR":"康寧路1段265號前","CB_DA":"1060503","CE_DA":"1060505","CO_TI":"依交維計畫訂定時間施工  日間施工9時30分至16時","TC_MA":"曾再村","TC_TL":"0988952679","TC_MA3":"阮冠豪","TC_TL3":"0976941031","NPURP":"市政建設","DTYPE":null},{"_id":"45","AC_NO":"106001683","ST_NO":"1","SNO":"5","APPMODE":"0","X":"301002.451","Y":"2781597.475","APPTIME":"1060509092138","APP_NAME":"自來水陽明","C_NAME":"北投","ADDR":"珠海路與長壽路交口至復興加壓站","CB_DA":"1060502","CE_DA":"1060630","CO_TI":"日間施工9時30分至16時","TC_MA":"曾崇賢","TC_TL":"0982777697","TC_MA3":"邱奕仁","TC_TL3":"0970502405","NPURP":"管線單位需求-既設管線改善","DTYPE":null},{"_id":"46","AC_NO":"106001699","ST_NO":"1","SNO":"1","APPMODE":"0","X":"302726.476","Y":"2772932.031","APPTIME":"1060509095403","APP_NAME":"自來水東區","C_NAME":"中山","ADDR":"中山北路2段183巷口(近中山北路)","CB_DA":"1060507","CE_DA":"1060509","CO_TI":"日間施工10時至15時","TC_MA":"盧啟弘","TC_TL":"0979213252","TC_MA3":"陳重瑋","TC_TL3":"0922508755","NPURP":"市政建設","DTYPE":null},{"_id":"47","AC_NO":"106001743","ST_NO":"1","SNO":"1","APPMODE":"0","X":"299727.359","Y":"2769015.183","APPTIME":"1060509093011","APP_NAME":"電信南區","C_NAME":"萬華","ADDR":"西藏路267號、281號至285號及289號附近","CB_DA":"1060509","CE_DA":"1060512","CO_TI":"日間施工9時30分至16時","TC_MA":"李華宇","TC_TL":"0937857904","TC_MA3":"楊水生","TC_TL3":"0988707609","NPURP":"管線單位需求-既設管線改善","DTYPE":null},{"_id":"48","AC_NO":"106001793","ST_NO":"1","SNO":"2","APPMODE":"0","X":"308031.069","Y":"2765748.032","APPTIME":"1060509100239","APP_NAME":"交工處","C_NAME":"文山","ADDR":"木柵路4段與木柵路4段149巷口(博嘉里)","CB_DA":"1060505","CE_DA":"1060519","CO_TI":"平日日間施工10時至15時，週休二日夜間施工23時至翌日5時30分","TC_MA":"黃琨淞","TC_TL":"0919325365","TC_MA3":"陳家志","TC_TL3":"0978218978","NPURP":"市政建設","DTYPE":null},{"_id":"49","AC_NO":"106001811","ST_NO":"1","SNO":"1","APPMODE":"0","X":"312595.849","Y":"2770335.4","APPTIME":"1060509093046","APP_NAME":"自來水東區","C_NAME":"南港","ADDR":"舊莊街1段145巷口對面","CB_DA":"1060509","CE_DA":"1060510","CO_TI":"依交維計畫訂定時間施工  日間施工9時30分至16時","TC_MA":"董士誠","TC_TL":"0979213238","TC_MA3":"詹世鴻","TC_TL3":"0933863371","NPURP":"市政建設","DTYPE":null},{"_id":"50","AC_NO":"106001820","ST_NO":"1","SNO":"1","APPMODE":"0","X":"301424.187","Y":"2773378.314","APPTIME":"1060509101640","APP_NAME":"衛工處","C_NAME":"大同","ADDR":"迪化街2段190巷22號附近地區","CB_DA":"1060508","CE_DA":"1060511","CO_TI":"日間施工9時30分至16時","TC_MA":"邱啟禎","TC_TL":"0988383145","TC_MA3":"林秉謙","TC_TL3":"0955671468","NPURP":"市政建設","DTYPE":null},{"_id":"51","AC_NO":"106001821","ST_NO":"1","SNO":"1","APPMODE":"0","X":"301559.166","Y":"2772955.939","APPTIME":"1060509093033","APP_NAME":"衛工處","C_NAME":"大同","ADDR":"延平北路3段18巷12附近地區","CB_DA":"1060509","CE_DA":"1060512","CO_TI":"日間施工9時30分至16時","TC_MA":"蕭志宏","TC_TL":"0933063248","TC_MA3":"林禮驅","TC_TL3":"0906109788","NPURP":"市政建設","DTYPE":null},{"_id":"52","AC_NO":"106001864","ST_NO":"1","SNO":"2","APPMODE":"3","X":"308408.7","Y":"2774196.07","APPTIME":"1060509111201","APP_NAME":"麗冠有線","C_NAME":"內湖","ADDR":"江南街71巷與瑞光路235巷交叉口","CB_DA":"1060502","CE_DA":"1060503","CO_TI":"日間施工9時30分至16時單方向可留設3.5公尺以上空間通行","TC_MA":"陳韋旭","TC_TL":"0977039365","TC_MA3":"陳宜豐","TC_TL3":"0922066888","NPURP":"管線單位需求-建設需求","DTYPE":null},{"_id":"53","AC_NO":"106001870","ST_NO":"1","SNO":"2","APPMODE":"3","X":"302398.62","Y":"2769210.198","APPTIME":"1060509094849","APP_NAME":"聯維有線","C_NAME":"中正","ADDR":"羅斯福路1段58巷17弄與南昌街1段125巷交叉口","CB_DA":"1060502","CE_DA":"1060504","CO_TI":"日間施工9時30分至16時","TC_MA":"林政雄","TC_TL":"0962025266","TC_MA3":"洪昇澤","TC_TL3":"0937331421","NPURP":"管線單位需求-建設需求","DTYPE":null},{"_id":"54","AC_NO":"106001875","ST_NO":"1","SNO":"1","APPMODE":"0","X":"301989.897","Y":"2772101.859","APPTIME":"1060509094200","APP_NAME":"自來水北區","C_NAME":"大同","ADDR":"星明里重慶北路2段73巷全巷","CB_DA":"1060508","CE_DA":"1060521","CO_TI":"日間施工9時30分至16時","TC_MA":"呂明杰","TC_TL":"0979213290","TC_MA3":"李秉聰","TC_TL3":"0927300091","NPURP":"管線單位需求-既設管線改善","DTYPE":null},{"_id":"55","AC_NO":"106001913","ST_NO":"1","SNO":"1","APPMODE":"0","X":"311033.113","Y":"2774154.84","APPTIME":"1060509091135","APP_NAME":"郭燊貴","C_NAME":"內湖","ADDR":"成功路5段45巷與金龍路326巷交叉口旁","CB_DA":"1060509","CE_DA":"1060510","CO_TI":"日間施工9時30分至16時單方向可留設3.5公尺以上空間通行","TC_MA":"馬泰宇","TC_TL":"0937195158","TC_MA3":"許原寶","TC_TL3":"0927767378","NPURP":"民生需求-新建房屋","DTYPE":null},{"_id":"56","AC_NO":"106001938","ST_NO":"1","SNO":"2","APPMODE":"0","X":"301005.778","Y":"2770858.914","APPTIME":"1060509111725","APP_NAME":"衛工處","C_NAME":"萬華","ADDR":"武昌街2段80號及102號附近地區","CB_DA":"1060508","CE_DA":"1060510","CO_TI":"日間施工9時30分至16時","TC_MA":"郭忻凱","TC_TL":"0920419296","TC_MA3":"祝聖棠","TC_TL3":"0926039724","NPURP":"市政建設","DTYPE":null},{"_id":"57","AC_NO":"106001942","ST_NO":"1","SNO":"2","APPMODE":"0","X":"302420.981","Y":"2769020.128","APPTIME":"1060509093123","APP_NAME":"自來水西區","C_NAME":"中正","ADDR":"南昌路2段9巷口至羅斯福路二段8巷口(南福里)","CB_DA":"1060505","CE_DA":"1060522","CO_TI":"日間施工9時30分至16時","TC_MA":"張世強","TC_TL":"0921826069","TC_MA3":"李榮寮","TC_TL3":"0955053810","NPURP":"市政建設","DTYPE":null},{"_id":"58","AC_NO":"106001944","ST_NO":"1","SNO":"1","APPMODE":"0","X":"302944.209","Y":"2776318.489","APPTIME":"1060509114835","APP_NAME":"電信士林","C_NAME":"士林","ADDR":"文林路416號前","CB_DA":"1060508","CE_DA":"1060509","CO_TI":"日間施工9時30分至16時","TC_MA":"王芬滄","TC_TL":"0937026747","TC_MA3":"李益福","TC_TL3":"0917183688","NPURP":"民生需求-舊有用戶","DTYPE":null},{"_id":"83","AC_NO":"10601180","ST_NO":"0","SNO":"1","APPMODE":"5","X":"301842.415","Y":"2770881.305","APPTIME":"1060509102722","APP_NAME":"新工處","C_NAME":"中正","ADDR":"漢口街1段27號","CB_DA":"1060502","CE_DA":"1060612","CO_TI":null,"TC_MA":"孫瑋銘","TC_TL":"0930932617","TC_MA3":"吳彥廷","TC_TL3":"0970947121","NPURP":"道路維護施工","DTYPE":null},{"_id":"59","AC_NO":"106001945","ST_NO":"1","SNO":"1","APPMODE":"0","X":"306539.57","Y":"2771816.812","APPTIME":"1060509092133","APP_NAME":"電信東區","C_NAME":"松山","ADDR":"南京東路5段59巷31弄1號至33號附近","CB_DA":"1060508","CE_DA":"1060512","CO_TI":"日間施工9時30分至16時","TC_MA":"紀弘亮","TC_TL":"0910380815","TC_MA3":"陳榮川","TC_TL3":"0963715879","NPURP":"管線單位需求-既設管線改善","DTYPE":null},{"_id":"60","AC_NO":"106001948","ST_NO":"1","SNO":"1","APPMODE":"0","X":"306147.692","Y":"2765381.042","APPTIME":"1060509092226","APP_NAME":"自來水南區","C_NAME":"文山","ADDR":"興隆路3段304巷97號","CB_DA":"1060508","CE_DA":"1060509","CO_TI":"日間施工9時30分至16時","TC_MA":"王耀霖","TC_TL":"0979213263","TC_MA3":"謝奕民","TC_TL3":"0987735532","NPURP":"民生需求-新建房屋","DTYPE":null},{"_id":"61","AC_NO":"106001950","ST_NO":"1","SNO":"1","APPMODE":"0","X":"304043.026","Y":"2770388.508","APPTIME":"1060509095302","APP_NAME":"自來水南區","C_NAME":"大安","ADDR":"新生南路1段103巷33號對面","CB_DA":"1060508","CE_DA":"1060509","CO_TI":"日間施工9時30分至16時","TC_MA":"王耀霖","TC_TL":"0979213263","TC_MA3":"李豪維","TC_TL3":"0956007340","NPURP":"民生需求-新建房屋","DTYPE":null},{"_id":"62","AC_NO":"106001956-3","ST_NO":"1","SNO":"1","APPMODE":"0","X":"305544.618","Y":"2765825.751","APPTIME":"1060509095904","APP_NAME":"電信南區","C_NAME":"文山","ADDR":"興隆路2段96巷26-1號旁","CB_DA":"1060508","CE_DA":"1060509","CO_TI":"日間施工9時30分至16時","TC_MA":"吳俊逸","TC_TL":"0932894341","TC_MA3":"王書嫻","TC_TL3":"0988621812","NPURP":"民生需求-新建房屋","DTYPE":null},{"_id":"63","AC_NO":"106001964","ST_NO":"1","SNO":"1","APPMODE":"0","X":"305280.568","Y":"2768550.201","APPTIME":"1060509091143","APP_NAME":"電信南區","C_NAME":"大安","ADDR":"和平東路3段70號至70-3號人行道、樂業街41巷16弄4號、敦化南路2段172巷4號至30號","CB_DA":"1060509","CE_DA":"1060511","CO_TI":"日間施工9時30分至16時","TC_MA":"王乘運","TC_TL":"0928230074","TC_MA3":"陳建嘉","TC_TL3":"0986159328","NPURP":"管線單位需求-既設管線改善","DTYPE":null},{"_id":"64","AC_NO":"106001988","ST_NO":"1","SNO":"1","APPMODE":"0","X":"305035.843","Y":"2775424.619","APPTIME":"1060509085015","APP_NAME":"水利處","C_NAME":"中山","ADDR":"北安路501巷81弄登山口附近","CB_DA":"1060508","CE_DA":"1060626","CO_TI":"日間施工9時30分至16時","TC_MA":"鄭木祥","TC_TL":"0978552038","TC_MA3":"彭秉鈞","TC_TL3":"0917526418","NPURP":"市政建設","DTYPE":null},{"_id":"65","AC_NO":"106001995","ST_NO":"1","SNO":"1","APPMODE":"0","X":"303010.858","Y":"2768839.338","APPTIME":"1060509093009","APP_NAME":"微笑單車","C_NAME":"大安","ADDR":"和平東路1段/金山南路二段口西南側(和平金山路口)(古莊里)","CB_DA":"1060508","CE_DA":"1060522","CO_TI":"日間施工9時30分至16時","TC_MA":"楊隆興","TC_TL":"0927078767","TC_MA3":"陳宥任","TC_TL3":"0963360224","NPURP":"市政建設","DTYPE":null},{"_id":"66","AC_NO":"106002054","ST_NO":"1","SNO":"2","APPMODE":"0","X":"301210.909","Y":"2770822.599","APPTIME":"1060509072242","APP_NAME":"公園處","C_NAME":"萬華","ADDR":"漢中街(漢口街2段至武昌街2段西門徒步區)(106-TC-012)","CB_DA":"1060508","CE_DA":"1060512","CO_TI":"日間施工7時至15時","TC_MA":"陳安寶","TC_TL":"0936534189","TC_MA3":"黃尹彥","TC_TL3":"0983676040","NPURP":"市政建設","DTYPE":null},{"_id":"67","AC_NO":"10600309","ST_NO":"0","SNO":"64","APPMODE":"5","X":"304901.986","Y":"2774252.516","APPTIME":"1060509100254","APP_NAME":"新工處","C_NAME":"中山","ADDR":"大直橋及彩虹橋","CB_DA":"1060217","CE_DA":"1060709","CO_TI":null,"TC_MA":"楊宗諺","TC_TL":"0939178958","TC_MA3":"蔡承翰","TC_TL3":"0968210777","NPURP":"道路維護施工","DTYPE":null},{"_id":"68","AC_NO":"10600724","ST_NO":"0","SNO":"23","APPMODE":"5","X":"312614.171","Y":"2772011.484","APPTIME":"1060509092237","APP_NAME":"新工處","C_NAME":"內湖","ADDR":"南港橋及民權大橋","CB_DA":"1060330","CE_DA":"1060704","CO_TI":null,"TC_MA":"蘇俊哲","TC_TL":"0933346898","TC_MA3":"高興樣","TC_TL3":"0917152783","NPURP":"道路維護施工","DTYPE":null},{"_id":"69","AC_NO":"10600734","ST_NO":"0","SNO":"19","APPMODE":"5","X":"302792.554","Y":"2773723.321","APPTIME":"1060509085946","APP_NAME":"新工處","C_NAME":"中山","ADDR":"中山北路3段花博圓山公園側人行道鋪面改善工程(含圓山派出所前人行道)","CB_DA":"1060405","CE_DA":"1060603","CO_TI":null,"TC_MA":"柯柏存","TC_TL":"0980530015","TC_MA3":"張晉嘉","TC_TL3":"0910690180","NPURP":"道路維護施工","DTYPE":null},{"_id":"70","AC_NO":"10600764","ST_NO":"0","SNO":"26","APPMODE":"5","X":"301603.26","Y":"2770501.33","APPTIME":"1060509081259","APP_NAME":"新工處","C_NAME":"中正","ADDR":"博愛路(衡陽路至寶慶路)西側人行道鋪面更新","CB_DA":"1060407","CE_DA":"1060511","CO_TI":null,"TC_MA":"王科傑","TC_TL":"0970682193","TC_MA3":"林志昌","TC_TL3":"0930675365","NPURP":"道路維護施工","DTYPE":null},{"_id":"71","AC_NO":"10600811","ST_NO":"0","SNO":"29","APPMODE":"5","X":"299626.425","Y":"2768814.595","APPTIME":"1060509091527","APP_NAME":"新工處","C_NAME":"萬華","ADDR":"萬華區興義街（環河南路3段至寶興街）側溝蓋更新工程","CB_DA":"1060407","CE_DA":"1060603","CO_TI":null,"TC_MA":"陳昱愷","TC_TL":"0937601585","TC_MA3":"蔡高亮","TC_TL3":"0936080804","NPURP":"道路維護施工","DTYPE":null},{"_id":"72","AC_NO":"10600942","ST_NO":"0","SNO":"23","APPMODE":"5","X":"310063.901","Y":"2766134.436","APPTIME":"1060509080808","APP_NAME":"新工處","C_NAME":"文山","ADDR":"文山區木柵路5段(自文和橋至新北市端)、羅斯福路六段滬江中學站遷移鋪面更新、興隆路三段與辛亥路四段交叉口增設車阻、景隆街19巷口(變電所圍牆側)人行道更新\r\n","CB_DA":"1060418","CE_DA":"1060611","CO_TI":null,"TC_MA":"陳孟緯","TC_TL":"0960535036","TC_MA3":"林勇茂","TC_TL3":"0982334796","NPURP":"道路維護施工","DTYPE":null},{"_id":"73","AC_NO":"10600942","ST_NO":"0","SNO":"24","APPMODE":"5","X":"304532.914","Y":"2765857.969","APPTIME":"1060509081404","APP_NAME":"新工處","C_NAME":"文山","ADDR":"文山區木柵路5段(自文和橋至新北市端)、羅斯福路六段滬江中學站遷移鋪面更新、興隆路三段與辛亥路四段交叉口增設車阻、景隆街19巷口(變電所圍牆側)人行道更新\r\n","CB_DA":"1060418","CE_DA":"1060611","CO_TI":null,"TC_MA":"陳孟緯","TC_TL":"0960535036","TC_MA3":"林勇茂","TC_TL3":"0982334796","NPURP":"道路維護施工","DTYPE":null},{"_id":"74","AC_NO":"10600980","ST_NO":"0","SNO":"1","APPMODE":"5","X":"305684.138","Y":"2769190.625","APPTIME":"1060509101546","APP_NAME":"新工處","C_NAME":"大安","ADDR":"四維路198巷39弄、四維路198巷22號、安和路2段99號。","CB_DA":"1060505","CE_DA":"1060518","CO_TI":null,"TC_MA":"宋旭明","TC_TL":"0984316529","TC_MA3":"施愷迪","TC_TL3":"0939869891","NPURP":"道路維護施工","DTYPE":null},{"_id":"75","AC_NO":"10601001","ST_NO":"0","SNO":"11","APPMODE":"5","X":"310582.724","Y":"2775290.633","APPTIME":"1060509091000","APP_NAME":"新工處","C_NAME":"內湖","ADDR":"內湖區成功路4段(294巷口至334號及372號前)及成功路5段(5號至32號)","CB_DA":"1060425","CE_DA":"1060524","CO_TI":null,"TC_MA":"張晉源","TC_TL":"0937903677","TC_MA3":"周振賢","TC_TL3":"0955097837","NPURP":"道路維護施工","DTYPE":null},{"_id":"76","AC_NO":"10601002","ST_NO":"0","SNO":"1","APPMODE":"5","X":"304356.376","Y":"2769526.327","APPTIME":"1060509085737","APP_NAME":"新工處","C_NAME":"大安","ADDR":"建國南路二段11巷溝蓋更新","CB_DA":"1060424","CE_DA":"1060515","CO_TI":null,"TC_MA":"王永翰","TC_TL":"0953012993","TC_MA3":"江元鑾","TC_TL3":"0931117266","NPURP":"道路維護施工","DTYPE":null},{"_id":"77","AC_NO":"10601008","ST_NO":"0","SNO":"2","APPMODE":"5","X":"304878.097","Y":"2769605.213","APPTIME":"1060509083147","APP_NAME":"新工處","C_NAME":"大安","ADDR":"新生南路三段86巷臨新生南路口、和平東路(師範大學旁)人行道座椅老舊更新、信義路與復興南路交叉口東北角與東南角鋪面改善及敦化南路與信義路口東南角緣石修改","CB_DA":"1060421","CE_DA":"1060531","CO_TI":null,"TC_MA":"房翔棟","TC_TL":"0937882083","TC_MA3":"林家俊","TC_TL3":"0915670230","NPURP":"道路維護施工","DTYPE":null},{"_id":"78","AC_NO":"10601026","ST_NO":"0","SNO":"7","APPMODE":"5","X":"307383.896","Y":"2764913.851","APPTIME":"1060509093837","APP_NAME":"華林營造股份有限公司","C_NAME":"文山","ADDR":"台北市文山區久康街169巷(全巷)","CB_DA":"1060502","CE_DA":"1060602","CO_TI":null,"TC_MA":"莊洲民","TC_TL":"0933896533","TC_MA3":"林庭慶","TC_TL3":"0927791532","NPURP":"道路維護施工","DTYPE":null},{"_id":"79","AC_NO":"10601057","ST_NO":"0","SNO":"14","APPMODE":"5","X":"306898.362","Y":"2769874.618","APPTIME":"1060509083738","APP_NAME":"新工處","C_NAME":"信義","ADDR":"市府路(松壽至松高)","CB_DA":"1060426","CE_DA":"1060624","CO_TI":null,"TC_MA":"林靖","TC_TL":"0985321141","TC_MA3":"陳以儒","TC_TL3":"0985060308","NPURP":"道路維護施工","DTYPE":null},{"_id":"80","AC_NO":"10601084","ST_NO":"0","SNO":"6","APPMODE":"5","X":"306822.24","Y":"2772840.529","APPTIME":"1060509092022","APP_NAME":"新工處","C_NAME":"松山","ADDR":"民權東路4段(三民路至新中街)","CB_DA":"1060502","CE_DA":"1060528","CO_TI":null,"TC_MA":"顏宇隆","TC_TL":"0989175065","TC_MA3":"蔡宗霖","TC_TL3":"0958730527","NPURP":"道路維護施工","DTYPE":null},{"_id":"81","AC_NO":"10601161","ST_NO":"0","SNO":"1","APPMODE":"5","X":"305275.695","Y":"2770427.494","APPTIME":"1060509095232","APP_NAME":"電信北區","C_NAME":"大安","ADDR":"敦化南路1段232巷(忠孝東路4段126號旁)","CB_DA":"1060508","CE_DA":"1060512","CO_TI":null,"TC_MA":"魏文章","TC_TL":"0933899874","TC_MA3":"吳書銘","TC_TL3":"0988770556","NPURP":"道路維護施工","DTYPE":null},{"_id":"82","AC_NO":"10601179","ST_NO":"0","SNO":"7","APPMODE":"5","X":"300094.078","Y":"2780969.421","APPTIME":"1060509100117","APP_NAME":"新工處","C_NAME":"北投","ADDR":"中央北路二段與大業路口","CB_DA":"1060502","CE_DA":"1060715","CO_TI":null,"TC_MA":"薛宏昌","TC_TL":"0987249006","TC_MA3":"陳裕方","TC_TL3":"0985060015","NPURP":"道路維護施工","DTYPE":null},{"_id":"84","AC_NO":"10601192","ST_NO":"0","SNO":"2","APPMODE":"5","X":"300869.833","Y":"2770201.501","APPTIME":"1060509090219","APP_NAME":"新工處","C_NAME":"萬華","ADDR":"昆明街201巷、桂林路29巷","CB_DA":"1060508","CE_DA":"1060518","CO_TI":null,"TC_MA":"賴芝宇","TC_TL":"0937010687","TC_MA3":"李泰興","TC_TL3":"0933879220","NPURP":"道路維護施工","DTYPE":null},{"_id":"85","AC_NO":"10601194","ST_NO":"0","SNO":"4","APPMODE":"5","X":"307880.985","Y":"2778781.042","APPTIME":"1060509081944","APP_NAME":"新工處","C_NAME":"士林","ADDR":"至善路三段150巷至橋頭臨溪側人行道\r\n石牌路2段130巷口","CB_DA":"1060503","CE_DA":"1060601","CO_TI":null,"TC_MA":"陳志榮","TC_TL":"0980123595","TC_MA3":"潘聰富","TC_TL3":"0970966269","NPURP":"道路維護施工","DTYPE":null},{"_id":"86","AC_NO":"10601219","ST_NO":"0","SNO":"3","APPMODE":"5","X":"306156.384","Y":"2770397.804","APPTIME":"1060509090905","APP_NAME":"新工處","C_NAME":"大安","ADDR":"大安區捷運國父紀念館站2號出口後方僑安停車場前","CB_DA":"1060504","CE_DA":"1060617","CO_TI":null,"TC_MA":"陳孟緯","TC_TL":"0960535036","TC_MA3":"巫偉銘","TC_TL3":"0935203389","NPURP":"道路維護施工","DTYPE":null},{"_id":"87","AC_NO":"10601252","ST_NO":"0","SNO":"2","APPMODE":"5","X":"301303.876","Y":"2775969.393","APPTIME":"1060509084834","APP_NAME":"新工處","C_NAME":"士林","ADDR":"社中街251巷路面及兩側溝蓋更新、社中街210巷溝蓋。\r\n","CB_DA":"1060508","CE_DA":"1060518","CO_TI":null,"TC_MA":"劉人豪","TC_TL":"0989431090","TC_MA3":"李俊揚","TC_TL3":"0958302957","NPURP":"道路維護施工","DTYPE":null},{"_id":"88","AC_NO":"10601280","ST_NO":"0","SNO":"1","APPMODE":"5","X":"304234.405","Y":"2769400.403","APPTIME":"1060509101701","APP_NAME":"新工處","C_NAME":"大安","ADDR":"建國南路二段本線上大安森林公園2號出口。","CB_DA":"1060505","CE_DA":"1060519","CO_TI":null,"TC_MA":"賴芝宇","TC_TL":"0937010687","TC_MA3":"鄭進興","TC_TL3":"0980796905","NPURP":"道路維護施工","DTYPE":null},{"_id":"89","AC_NO":"10601290","ST_NO":"0","SNO":"2","APPMODE":"5","X":"306053.493","Y":"2768272.803","APPTIME":"1060509100030","APP_NAME":"新工處","C_NAME":"大安","ADDR":"大安區安居街(自樂業街至和平東路3段口)","CB_DA":"1060508","CE_DA":"1060522","CO_TI":null,"TC_MA":"趙志融","TC_TL":"0936872412","TC_MA3":"曾紹軒","TC_TL3":"0912213360","NPURP":"道路維護施工","DTYPE":null},{"_id":"90","AC_NO":"10601295","ST_NO":"0","SNO":"1","APPMODE":"5","X":"299456.501","Y":"2781073.898","APPTIME":"1060509101031","APP_NAME":"新工處","C_NAME":"北投","ADDR":"中央稻香車行地下道、中央立功車行地下道美化改善工程","CB_DA":"1060508","CE_DA":"1060607","CO_TI":null,"TC_MA":"黃勇勝","TC_TL":"0985209280","TC_MA3":"康瑋倫","TC_TL3":"0938117268","NPURP":"道路維護施工","DTYPE":null},{"_id":"91","AC_NO":"1062015395","ST_NO":"0","SNO":"1","APPMODE":"6","X":"307774.231","Y":"2774982.981","APPTIME":"1060509110834","APP_NAME":"電信東區","C_NAME":"內湖","ADDR":"麗山街內湖路1段437巷一帶附近","CB_DA":"1060509","CE_DA":"1060513","CO_TI":"09:30-16:00","TC_MA":"劉勝宗","TC_TL":"劉勝宗","TC_MA3":"涂德賢","TC_TL3":"0932238963","NPURP":"人手孔施工","DTYPE":null},{"_id":"92","AC_NO":"E41060003","ST_NO":"0","SNO":"1","APPMODE":"4","X":"306305.618","Y":"2771213.55","APPTIME":"1060429195123","APP_NAME":"台電輸變電","C_NAME":"松山","ADDR":"光復北路光復北路八德路口","CB_DA":"1060429","CE_DA":"1060508","CO_TI":null,"TC_MA":"葉信宏","TC_TL":"0932312480","TC_MA3":"林晏暘","TC_TL3":"0982472959","NPURP":"搶修","DTYPE":null},{"_id":"93","AC_NO":"EN1060017","ST_NO":"0","SNO":"2","APPMODE":"3","X":"312248.274","Y":"2769894.886","APPTIME":"1060509114825","APP_NAME":"台電北區","C_NAME":"南港","ADDR":"研究院路3段10巷對面","CB_DA":"1060505","CE_DA":"1060505","CO_TI":null,"TC_MA":"林進豊","TC_TL":"0928287045","TC_MA3":"陳傳芳","TC_TL3":"0932212892","NPURP":"搶修","DTYPE":null},{"_id":"94","AC_NO":"GT1060153","ST_NO":"0","SNO":"1","APPMODE":"4","X":"303269.228","Y":"2769087.497","APPTIME":"1060509094534","APP_NAME":"大台北瓦斯","C_NAME":"大安","ADDR":"金山南路2段159巷39號前","CB_DA":"1060509","CE_DA":"1060513","CO_TI":null,"TC_MA":"陶進明","TC_TL":"0939667789","TC_MA3":"陶進明","TC_TL3":"0939667789","NPURP":"搶修","DTYPE":null},{"_id":"95","AC_NO":"GT1060154","ST_NO":"0","SNO":"1","APPMODE":"4","X":"302343.192","Y":"2772527.722","APPTIME":"1060509100500","APP_NAME":"大台北瓦斯","C_NAME":"大同","ADDR":"雙連街89、91號前等2處","CB_DA":"1060509","CE_DA":"1060513","CO_TI":null,"TC_MA":"黃智偉","TC_TL":"0982100201","TC_MA3":"王威","TC_TL3":"0987929547","NPURP":"搶修","DTYPE":null},{"_id":"96","AC_NO":"GT1060155","ST_NO":"0","SNO":"1","APPMODE":"4","X":"301388.135","Y":"2772539.047","APPTIME":"1060509092916","APP_NAME":"大台北瓦斯","C_NAME":"大同","ADDR":"迪化街250號前","CB_DA":"1060509","CE_DA":"1060513","CO_TI":null,"TC_MA":"甘興杰","TC_TL":"0911225887","TC_MA3":"嚴獻宗","TC_TL3":"0931226001","NPURP":"搶修","DTYPE":null},{"_id":"97","AC_NO":"WS1060107","ST_NO":"0","SNO":"1","APPMODE":"4","X":"304323.125","Y":"2770871.524","APPTIME":"1060509104913","APP_NAME":"自來水南區","C_NAME":"中山","ADDR":"八德路2段174巷15弄口旁","CB_DA":"1060509","CE_DA":"1060509","CO_TI":null,"TC_MA":"李承鴻","TC_TL":"0979213258","TC_MA3":"劉育昌","TC_TL3":"0963583315","NPURP":"搶修","DTYPE":null},{"_id":"98","AC_NO":"WW1060054","ST_NO":"0","SNO":"1","APPMODE":"4","X":"300206.538","Y":"2769660.084","APPTIME":"1060509103632","APP_NAME":"自來水西區","C_NAME":"萬華","ADDR":"大理街114號(糖部里)","CB_DA":"1060509","CE_DA":"1060509","CO_TI":null,"TC_MA":"陳子俊","TC_TL":"0939028832","TC_MA3":"江柏泉","TC_TL3":"0930718273","NPURP":"搶修","DTYPE":null},{"_id":"99","AC_NO":"WY1060144","ST_NO":"0","SNO":"1","APPMODE":"4","X":"302125.612","Y":"2779044.066","APPTIME":"1060509094915","APP_NAME":"自來水陽明","C_NAME":"北投","ADDR":"立農街2段301號","CB_DA":"1060509","CE_DA":"1060509","CO_TI":null,"TC_MA":"白耀宏","TC_TL":"0922293705","TC_MA3":"吳國棟","TC_TL3":"0981567318","NPURP":"搶修","DTYPE":null}]}}